ffile/__init__.py
ffile/ffile.py
ffile/tests/__init__.py
ffile/tests/test_Ffile.py
ffile/tests/test_cli.py
ffile-2.0.0.dist-info/LICENSE
ffile-2.0.0.dist-info/METADATA
ffile-2.0.0.dist-info/WHEEL
ffile-2.0.0.dist-info/entry_points.txt
ffile-2.0.0.dist-info/top_level.txt
ffile-2.0.0.dist-info/RECORD
