Metadata-Version: 2.1
Name: ffile
Version: 2.0.0
Summary: F-strings for a whole file.
Home-page: https://github.com/matthew-sochor/ffile
Author: Matthew Sochor
Author-email: matthew.sochor@gmail.com
License: MIT
Download-URL: https://github.com/matthew-sochor/ffile
Platform: UNKNOWN
Requires-Python: >=3.6
